project_x_py/__init__.py
project_x_py/config.py
project_x_py/event_bus.py
project_x_py/exceptions.py
project_x_py/models.py
project_x_py/order_templates.py
project_x_py/order_tracker.py
project_x_py/py.typed
project_x_py/trading_suite.py
project_x_py/client/__init__.py
project_x_py/client/auth.py
project_x_py/client/base.py
project_x_py/client/cache.py
project_x_py/client/http.py
project_x_py/client/market_data.py
project_x_py/client/trading.py
project_x_py/data/__init__.py
project_x_py/data/mmap_storage.py
project_x_py/indicators/__init__.py
project_x_py/indicators/base.py
project_x_py/indicators/candlestick.py
project_x_py/indicators/fvg.py
project_x_py/indicators/lorenz.py
project_x_py/indicators/momentum.py
project_x_py/indicators/order_block.py
project_x_py/indicators/overlap.py
project_x_py/indicators/volatility.py
project_x_py/indicators/volume.py
project_x_py/indicators/waddah_attar.py
project_x_py/order_manager/__init__.py
project_x_py/order_manager/bracket_orders.py
project_x_py/order_manager/core.py
project_x_py/order_manager/error_recovery.py
project_x_py/order_manager/order_types.py
project_x_py/order_manager/position_orders.py
project_x_py/order_manager/tracking.py
project_x_py/order_manager/utils.py
project_x_py/orderbook/__init__.py
project_x_py/orderbook/analytics.py
project_x_py/orderbook/base.py
project_x_py/orderbook/detection.py
project_x_py/orderbook/memory.py
project_x_py/orderbook/profile.py
project_x_py/orderbook/realtime.py
project_x_py/position_manager/__init__.py
project_x_py/position_manager/analytics.py
project_x_py/position_manager/core.py
project_x_py/position_manager/monitoring.py
project_x_py/position_manager/operations.py
project_x_py/position_manager/reporting.py
project_x_py/position_manager/risk.py
project_x_py/position_manager/tracking.py
project_x_py/realtime/__init__.py
project_x_py/realtime/batched_handler.py
project_x_py/realtime/circuit_breaker.py
project_x_py/realtime/connection_management.py
project_x_py-3.5.9.dist-info/METADATA
project_x_py-3.5.9.dist-info/WHEEL
project_x_py-3.5.9.dist-info/entry_points.txt
project_x_py-3.5.9.dist-info/licenses/LICENSE
project_x_py-3.5.9.dist-info/RECORD
