Metadata-Version: 2.4
Name: project-x-py
Version: 3.5.9
Summary: High-performance Python SDK for futures trading with real-time WebSocket data, technical indicators, order management, and market depth analysis
Project-URL: Homepage, https://github.com/TexasCoding/project-x-py
Project-URL: Documentation, https://texascoding.github.io/project-x-py/
Project-URL: Repository, https://github.com/TexasCoding/project-x-py.git
Project-URL: Bug Tracker, https://github.com/TexasCoding/project-x-py/issues
Project-URL: Changelog, https://github.com/TexasCoding/project-x-py/blob/main/CHANGELOG.md
Author-email: TexasCoding <jeff10278@me.com>
Maintainer-email: TexasCoding <jeff10278@me.com>
License: MIT
License-File: LICENSE
Keywords: api-client,financial-data,futures,market-data,projectx,real-time-data,topstepx,trading
Classifier: Development Status :: 4 - Beta
Classifier: Intended Audience :: Developers
Classifier: Intended Audience :: Financial and Insurance Industry
Classifier: License :: OSI Approved :: MIT License
Classifier: Operating System :: OS Independent
Classifier: Programming Language :: Python :: 3
Classifier: Programming Language :: Python :: 3.12
Classifier: Programming Language :: Python :: 3.13
Classifier: Topic :: Office/Business :: Financial :: Investment
Classifier: Topic :: Software Development :: Libraries :: Python Modules
Classifier: Typing :: Typed
Requires-Python: >=3.12
Requires-Dist: cachetools>=6.1.0
Requires-Dist: deprecated>=1.2.18
Requires-Dist: httpx[http2]>=0.27.0
Requires-Dist: lz4>=4.4.4
Requires-Dist: msgpack-python>=0.5.6
Requires-Dist: numpy>=2.3.2
Requires-Dist: orjson>=3.11.1
Requires-Dist: plotly>=6.3.0
Requires-Dist: polars>=1.31.0
Requires-Dist: pydantic>=2.11.7
Requires-Dist: pytz>=2025.2
Requires-Dist: pyyaml>=6.0.2
Requires-Dist: requests>=2.32.4
Requires-Dist: rich>=14.1.0
Requires-Dist: signalrcore>=0.9.5
Requires-Dist: uvloop>=0.21.0
Requires-Dist: websocket-client>=1.0.0
Provides-Extra: all
Requires-Dist: aioresponses>=0.7.6; extra == 'all'
Requires-Dist: black>=23.0.0; extra == 'all'
Requires-Dist: isort>=5.12.0; extra == 'all'
Requires-Dist: mike>=2.0.0; extra == 'all'
Requires-Dist: mkdocs-autorefs>=0.5.0; extra == 'all'
Requires-Dist: mkdocs-gen-files>=0.5.0; extra == 'all'
Requires-Dist: mkdocs-jupyter>=0.24.0; extra == 'all'
Requires-Dist: mkdocs-literate-nav>=0.6.0; extra == 'all'
Requires-Dist: mkdocs-material>=9.0.0; extra == 'all'
Requires-Dist: mkdocs-section-index>=0.3.0; extra == 'all'
Requires-Dist: mkdocs>=1.5.0; extra == 'all'
Requires-Dist: mkdocstrings[python]>=0.24.0; extra == 'all'
Requires-Dist: mypy>=1.0.0; extra == 'all'
Requires-Dist: pre-commit>=3.0.0; extra == 'all'
Requires-Dist: pymdown-extensions>=10.0; extra == 'all'
Requires-Dist: pytest-asyncio>=0.23.0; extra == 'all'
Requires-Dist: pytest-cov>=4.0.0; extra == 'all'
Requires-Dist: pytest-mock>=3.10.0; extra == 'all'
Requires-Dist: pytest>=7.0.0; extra == 'all'
Requires-Dist: requests-mock>=1.9.0; extra == 'all'
Requires-Dist: ruff>=0.12.3; extra == 'all'
Requires-Dist: signalrcore>=0.9.5; extra == 'all'
Requires-Dist: websocket-client>=1.0.0; extra == 'all'
Provides-Extra: dev
Requires-Dist: aioresponses>=0.7.6; extra == 'dev'
Requires-Dist: black>=23.0.0; extra == 'dev'
Requires-Dist: isort>=5.12.0; extra == 'dev'
Requires-Dist: mypy>=1.0.0; extra == 'dev'
Requires-Dist: pre-commit>=3.0.0; extra == 'dev'
Requires-Dist: pytest-asyncio>=0.23.0; extra == 'dev'
Requires-Dist: pytest-cov>=4.0.0; extra == 'dev'
Requires-Dist: pytest>=7.0.0; extra == 'dev'
Requires-Dist: ruff>=0.12.3; extra == 'dev'
Provides-Extra: docs
Requires-Dist: mike>=2.0.0; extra == 'docs'
Requires-Dist: mkdocs-autorefs>=0.5.0; extra == 'docs'
Requires-Dist: mkdocs-gen-files>=0.5.0; extra == 'docs'
Requires-Dist: mkdocs-jupyter>=0.24.0; extra == 'docs'
Requires-Dist: mkdocs-literate-nav>=0.6.0; extra == 'docs'
Requires-Dist: mkdocs-material>=9.0.0; extra == 'docs'
Requires-Dist: mkdocs-section-index>=0.3.0; extra == 'docs'
Requires-Dist: mkdocs>=1.5.0; extra == 'docs'
Requires-Dist: mkdocstrings[python]>=0.24.0; extra == 'docs'
Requires-Dist: pymdown-extensions>=10.0; extra == 'docs'
Provides-Extra: realtime
Requires-Dist: signalrcore>=0.9.5; extra == 'realtime'
Requires-Dist: websocket-client>=1.0.0; extra == 'realtime'
Provides-Extra: test
Requires-Dist: aioresponses>=0.7.6; extra == 'test'
Requires-Dist: pytest-asyncio>=0.23.0; extra == 'test'
Requires-Dist: pytest-cov>=4.0.0; extra == 'test'
Requires-Dist: pytest-mock>=3.10.0; extra == 'test'
Requires-Dist: pytest>=7.0.0; extra == 'test'
Requires-Dist: requests-mock>=1.9.0; extra == 'test'
